dbxparams/__init__.py
dbxparams/core.py
dbxparams/errors.py
dbxparams/types.py
dbxparams-0.1.17.dist-info/licenses/LICENSE
examples/notebook_usage.py
examples/sales_params.py
tests/__init__.py
tests/conftest.py
tests/test_core.py
tests/test_exceptions.py
dbxparams-0.1.17.dist-info/METADATA
dbxparams-0.1.17.dist-info/WHEEL
dbxparams-0.1.17.dist-info/top_level.txt
dbxparams-0.1.17.dist-info/RECORD
