Metadata-Version: 2.4
Name: dbxparams
Version: 0.1.17
Summary: Manage Databricks notebook parameters as Python classes
Author-email: Víctor Ferron <victordevaut@gmail.com>
License: MIT License
Classifier: Programming Language :: Python :: 3
Classifier: License :: OSI Approved :: MIT License
Classifier: Operating System :: OS Independent
Requires-Python: >=3.8
License-File: LICENSE
Dynamic: license-file
